{
    "sample": "260411-pwxd9sfy4r",
    "status": "reported",
    "custom": "frontend:32c3eaea-384d-4893-ba9e-e02de67ff1d8",
    "owner": "fe-hpt-04168b48dafbce6b7.recfut.net",
    "org_id": "7d6b1a28-20a8-42d8-9845-1fcd67f5ccbd",
    "meta": {
        "channel": "public"
    },
    "target": "9189499c98ba9a90ecebfb73b559d6bd44009fb7c58ed53f1a103a5b6e51a3f4_cavity.sh",
    "created": "2026-04-11T12:41:19Z",
    "completed": "2026-04-11T12:44:16Z",
    "score": 5,
    "sha256": "c2073a2775bba266659f4666957aefb8638ea369ba7f1595ac9e44ac2b0e43a1",
    "tasks": {
        "260411-pwxd9sfy4r-behavioral1": {
            "kind": "behavioral",
            "status": "reported",
            "tags": [
                "adware",
                "discovery",
                "spyware"
            ],
            "score": 3,
            "target": "9189499c98ba9a90ecebfb73b559d6bd44009fb7c58ed53f1a103a5b6e51a3f4_cavity.pdf",
            "backend": "sbx4m65",
            "resource": "win10v2004-20260130-en",
            "os": "windows10-2004-x64",
            "timeout": 150,
            "sigs": 7
        },
        "260411-pwxd9sfy4r-behavioral2": {
            "kind": "behavioral",
            "status": "reported",
            "tags": [
                "adware",
                "discovery",
                "spyware"
            ],
            "score": 3,
            "target": "9189499c98ba9a90ecebfb73b559d6bd44009fb7c58ed53f1a103a5b6e51a3f4_cavity.pdf",
            "backend": "sbx4m75",
            "resource": "win11-20260130-en",
            "os": "windows11-21h2-x64",
            "timeout": 150,
            "sigs": 7
        },
        "260411-pwxd9sfy4r-static1": {
            "kind": "static",
            "status": "reported",
            "tags": [
                "pdf"
            ],
            "score": 5,
            "sigs": 1
        }
    }
}