{
    "sample": "260411-qs7aqscs6w",
    "status": "reported",
    "custom": "frontend:e5ebffb2-7a32-4499-9405-cfb52cfef65a",
    "owner": "fe-hpt-04168b48dafbce6b7.recfut.net",
    "org_id": "7d6b1a28-20a8-42d8-9845-1fcd67f5ccbd",
    "meta": {
        "channel": "public"
    },
    "target": "0794add65a271388acc6ab87a0dc2fe47373b40921f22dec12c02f74fbe6b154_zipper.js",
    "created": "2026-04-11T13:32:29Z",
    "completed": "2026-04-11T13:35:56Z",
    "score": 8,
    "sha256": "8f2bea5f8a105d5066d86322ad32aa5ea778eeeaad2bef7277244627a7e4cf66",
    "tasks": {
        "260411-qs7aqscs6w-behavioral1": {
            "kind": "behavioral",
            "status": "reported",
            "tags": [
                "defense_evasion",
                "execution"
            ],
            "score": 8,
            "target": "0794add65a271388acc6ab87a0dc2fe47373b40921f22dec12c02f74fbe6b154_zipper.js",
            "backend": "sbx4m62",
            "resource": "win10v2004-20260130-en",
            "os": "windows10-2004-x64",
            "timeout": 150,
            "sigs": 8
        },
        "260411-qs7aqscs6w-behavioral2": {
            "kind": "behavioral",
            "status": "reported",
            "tags": [
                "defense_evasion",
                "execution"
            ],
            "score": 8,
            "target": "0794add65a271388acc6ab87a0dc2fe47373b40921f22dec12c02f74fbe6b154_zipper.js",
            "backend": "sbx4m60",
            "resource": "win11-20260130-en",
            "os": "windows11-21h2-x64",
            "timeout": 150,
            "sigs": 7
        },
        "260411-qs7aqscs6w-static1": {
            "kind": "static",
            "status": "reported",
            "score": 5,
            "sigs": 1
        }
    }
}