{
    "sample": "260411-ndvbhsf17y",
    "status": "reported",
    "custom": "frontend:f1be73a9-b2b3-4ceb-ac6e-c9a4f877fc15",
    "owner": "fe-hpt-04168b48dafbce6b7.recfut.net",
    "org_id": "7d6b1a28-20a8-42d8-9845-1fcd67f5ccbd",
    "meta": {
        "channel": "public"
    },
    "target": "0bfc2b5594e9563b60bdce2deb8d1bd3766a8a574bbc5dc604f4eaad5723fcf4_stack.py",
    "created": "2026-04-11T11:17:19Z",
    "completed": "2026-04-11T11:19:53Z",
    "score": 5,
    "sha256": "bb95c048b3d15c389620cae64ba5e93b4c76fe08085ed972956460ca35bcff9e",
    "tasks": {
        "260411-ndvbhsf17y-behavioral1": {
            "kind": "behavioral",
            "status": "reported",
            "tags": [
                "adware",
                "discovery",
                "spyware"
            ],
            "score": 3,
            "target": "0bfc2b5594e9563b60bdce2deb8d1bd3766a8a574bbc5dc604f4eaad5723fcf4_stack.pdf",
            "backend": "sbx4m65",
            "resource": "win10v2004-20260130-en",
            "os": "windows10-2004-x64",
            "timeout": 150,
            "sigs": 6
        },
        "260411-ndvbhsf17y-behavioral2": {
            "kind": "behavioral",
            "status": "reported",
            "tags": [
                "adware",
                "discovery",
                "spyware"
            ],
            "score": 3,
            "target": "0bfc2b5594e9563b60bdce2deb8d1bd3766a8a574bbc5dc604f4eaad5723fcf4_stack.pdf",
            "backend": "sbx4m65",
            "resource": "win11-20260130-en",
            "os": "windows11-21h2-x64",
            "timeout": 150,
            "sigs": 5
        },
        "260411-ndvbhsf17y-static1": {
            "kind": "static",
            "status": "reported",
            "tags": [
                "pdf"
            ],
            "score": 5,
            "sigs": 1
        }
    }
}