{
    "sample": "260523-wvyz2abt8x",
    "status": "reported",
    "custom": "frontend:ba4fbfca-7927-4541-b650-d001addf4a5a",
    "owner": "fe-hpt-04168b48dafbce6b7.recfut.net",
    "org_id": "7d6b1a28-20a8-42d8-9845-1fcd67f5ccbd",
    "meta": {
        "channel": "public"
    },
    "target": "262bb0abdf65d6d2baa592eb249d2693281a1c9c6180d1e46c57e79f52cb37b4_stack.js",
    "created": "2026-05-23T18:15:12Z",
    "completed": "2026-05-23T18:20:14Z",
    "score": 5,
    "sha256": "182402232626b1e41a6baf9c03d2182a619eba19244394014c59836a1e6aef00",
    "tasks": {
        "260523-wvyz2abt8x-behavioral1": {
            "kind": "behavioral",
            "status": "reported",
            "tags": [
                "execution"
            ],
            "score": 3,
            "target": "262bb0abdf65d6d2baa592eb249d2693281a1c9c6180d1e46c57e79f52cb37b4_stack.js",
            "backend": "sbx4m75",
            "resource": "win10v2004-20260513-en",
            "os": "windows10-2004-x64",
            "timeout": 150,
            "sigs": 1
        },
        "260523-wvyz2abt8x-behavioral2": {
            "kind": "behavioral",
            "status": "reported",
            "tags": [
                "execution"
            ],
            "score": 3,
            "target": "262bb0abdf65d6d2baa592eb249d2693281a1c9c6180d1e46c57e79f52cb37b4_stack.js",
            "backend": "sbx4m64",
            "resource": "win11-20260513-en",
            "os": "windows11-21h2-x64",
            "timeout": 150,
            "sigs": 1
        },
        "260523-wvyz2abt8x-static1": {
            "kind": "static",
            "status": "reported",
            "tags": [
                "pdf"
            ],
            "score": 5,
            "sigs": 1
        }
    }
}